cdk_eks_cluster_module/__init__.py
cdk_eks_cluster_module/py.typed
cdk_eks_cluster_module/_jsii/__init__.py
cdk_eks_cluster_module/_jsii/cdk-eks-cluster-module@0.0.36.jsii.tgz
cdk_eks_cluster_module-0.0.36.dist-info/LICENSE
cdk_eks_cluster_module-0.0.36.dist-info/METADATA
cdk_eks_cluster_module-0.0.36.dist-info/WHEEL
cdk_eks_cluster_module-0.0.36.dist-info/top_level.txt
cdk_eks_cluster_module-0.0.36.dist-info/RECORD
