Metadata-Version: 2.1
Name: cdk-eks-cluster-module
Version: 0.0.36
Summary: @smallcase/cdk-eks-cluster-module
Home-page: https://github.com/smallcase/cdk-eks-cluster-module.git
Author: @InfraTeam<bharat.parmar@smallcase.com>
License: Apache-2.0
Project-URL: Source, https://github.com/smallcase/cdk-eks-cluster-module.git
Classifier: Intended Audience :: Developers
Classifier: Operating System :: OS Independent
Classifier: Programming Language :: JavaScript
Classifier: Programming Language :: Python :: 3 :: Only
Classifier: Programming Language :: Python :: 3.9
Classifier: Programming Language :: Python :: 3.10
Classifier: Programming Language :: Python :: 3.11
Classifier: Typing :: Typed
Classifier: Development Status :: 5 - Production/Stable
Classifier: License :: OSI Approved
Requires-Python: ~=3.9
License-File: LICENSE
Requires-Dist: aws-cdk-lib ==2.169.0
Requires-Dist: constructs <11.0.0,>=10.0.5
Requires-Dist: jsii <2.0.0,>=1.119.0
Requires-Dist: publication >=0.0.3
Requires-Dist: typeguard <4.3.0,>=2.13.3
